envers/__init__.py
envers/__main__.py
envers/cli.py
envers/core.py
envers/crypt.py
envers/py.typed
envers-0.4.1.dist-info/LICENSE
envers-0.4.1.dist-info/METADATA
envers-0.4.1.dist-info/WHEEL
envers-0.4.1.dist-info/entry_points.txt
envers-0.4.1.dist-info/RECORD
