Metadata-Version: 2.1
Name: envers
Version: 0.4.1
Summary: Envers is a tool for handling environment files (e.g. .env) for multiple kind of environments with versioning
License: BSD 3 Clause
Author: Ivan Ogasawara
Author-email: ivan.ogasawara@gmail.com
Requires-Python: >=3.8.1,<4
Classifier: License :: Other/Proprietary License
Classifier: Programming Language :: Python :: 3
Classifier: Programming Language :: Python :: 3.9
Classifier: Programming Language :: Python :: 3.10
Classifier: Programming Language :: Python :: 3.11
Classifier: Programming Language :: Python :: 3.12
Requires-Dist: cryptography (>=41.0)
Requires-Dist: jinja2 (>=2)
Requires-Dist: python-dotenv (>=1.0)
Requires-Dist: pyyaml (>=5.0)
Requires-Dist: typer[all] (>=0.9.0)
Requires-Dist: typing-extensions (>=4.9.0)
